{"NT": {"7": {"success": 409, "total": 409}, "12": {"success": 0, "total": 428}, "16": {"success": 0, "total": 144}, "8": {"success": 522, "total": 522}, "17": {"success": 0, "total": 130}, "11": {"success": 0, "total": 319}, "6": {"success": 338, "total": 338}, "25": {"success": 0, "total": 49}, "15": {"success": 0, "total": 183}, "4": {"success": 163, "total": 163}, "9": {"success": 0, "total": 547}, "14": {"success": 0, "total": 246}, "20": {"success": 0, "total": 72}, "3": {"success": 83, "total": 83}, "10": {"success": 0, "total": 572}, "26": {"success": 0, "total": 14}, "19": {"success": 0, "total": 94}, "29": {"success": 0, "total": 36}, "22": {"success": 0, "total": 87}, "21": {"success": 0, "total": 58}, "5": {"success": 231, "total": 231}, "18": {"success": 0, "total": 30}, "23": {"success": 0, "total": 32}, "27": {"success": 0, "total": 59}, "13": {"success": 0, "total": 126}, "28": {"success": 0, "total": 13}, "24": {"success": 0, "total": 62}}, "T": {"15": {"success": 216, "total": 216}, "10": {"success": 552, "total": 552}, "25": {"success": 109, "total": 109}, "17": {"success": 139, "total": 139}, "4": {"success": 0, "total": 132}, "12": {"success": 551, "total": 551}, "29": {"success": 32, "total": 32}, "8": {"success": 0, "total": 300}, "21": {"success": 87, "total": 87}, "7": {"success": 0, "total": 360}, "6": {"success": 0, "total": 309}, "19": {"success": 92, "total": 92}, "22": {"success": 94, "total": 94}, "11": {"success": 449, "total": 449}, "16": {"success": 179, "total": 179}, "14": {"success": 222, "total": 222}, "9": {"success": 520, "total": 520}, "20": {"success": 100, "total": 100}, "30": {"success": 12, "total": 12}, "27": {"success": 80, "total": 80}, "18": {"success": 65, "total": 65}, "5": {"success": 0, "total": 64}, "13": {"success": 223, "total": 223}, "28": {"success": 30, "total": 30}, "23": {"success": 25, "total": 25}, "24": {"success": 11, "total": 11}}, "success_rate": 0.5534}