{"NT": {"1": {"success": 1129, "total": 1129}, "2": {"success": 0, "total": 1081}, "6": {"success": 0, "total": 340}, "7": {"success": 0, "total": 225}, "3": {"success": 0, "total": 553}, "13": {"success": 0, "total": 12}, "5": {"success": 0, "total": 393}, "9": {"success": 0, "total": 139}, "17": {"success": 0, "total": 67}, "4": {"success": 0, "total": 451}, "8": {"success": 0, "total": 65}, "10": {"success": 0, "total": 164}, "14": {"success": 0, "total": 74}, "12": {"success": 0, "total": 23}, "18": {"success": 0, "total": 60}, "27": {"success": 0, "total": 40}, "23": {"success": 0, "total": 21}, "30": {"success": 0, "total": 8}, "26": {"success": 0, "total": 4}, "15": {"success": 0, "total": 33}, "16": {"success": 0, "total": 33}, "11": {"success": 0, "total": 38}, "20": {"success": 0, "total": 20}}, "T": {"2": {"success": 759, "total": 759}, "1": {"success": 0, "total": 2635}, "3": {"success": 489, "total": 489}, "4": {"success": 199, "total": 199}, "7": {"success": 145, "total": 145}, "6": {"success": 159, "total": 159}, "5": {"success": 213, "total": 213}, "11": {"success": 71, "total": 71}, "8": {"success": 77, "total": 77}, "13": {"success": 18, "total": 18}, "10": {"success": 51, "total": 51}, "9": {"success": 75, "total": 75}, "31": {"success": 35, "total": 35}, "26": {"success": 5, "total": 5}, "16": {"success": 30, "total": 30}, "17": {"success": 27, "total": 27}, "18": {"success": 31, "total": 31}, "15": {"success": 8, "total": 8}}, "success_rate": 0.3521}