{"NT": {"1": {"success": 2489, "total": 2489}, "4": {"success": 0, "total": 509}, "6": {"success": 0, "total": 47}, "3": {"success": 0, "total": 852}, "2": {"success": 0, "total": 1001}, "9": {"success": 0, "total": 30}, "7": {"success": 0, "total": 16}, "5": {"success": 0, "total": 68}}, "T": {"1": {"success": 0, "total": 998}, "3": {"success": 1190, "total": 1190}, "4": {"success": 899, "total": 899}, "2": {"success": 1354, "total": 1354}, "5": {"success": 369, "total": 369}, "10": {"success": 11, "total": 11}, "6": {"success": 90, "total": 90}, "7": {"success": 35, "total": 35}, "9": {"success": 21, "total": 21}, "8": {"success": 21, "total": 21}}, "success_rate": 0.6479}