{"NT": {"1": {"success": 1213, "total": 1213}, "2": {"success": 0, "total": 1066}, "5": {"success": 0, "total": 315}, "3": {"success": 0, "total": 589}, "7": {"success": 0, "total": 273}, "4": {"success": 0, "total": 496}, "17": {"success": 0, "total": 86}, "11": {"success": 0, "total": 49}, "8": {"success": 0, "total": 221}, "6": {"success": 0, "total": 290}, "13": {"success": 0, "total": 83}, "18": {"success": 0, "total": 9}, "9": {"success": 0, "total": 83}, "10": {"success": 0, "total": 19}, "14": {"success": 0, "total": 19}, "16": {"success": 0, "total": 96}, "12": {"success": 0, "total": 27}, "20": {"success": 0, "total": 12}, "15": {"success": 0, "total": 29}}, "T": {"1": {"success": 0, "total": 3170}, "2": {"success": 544, "total": 544}, "4": {"success": 147, "total": 147}, "3": {"success": 345, "total": 345}, "6": {"success": 157, "total": 157}, "21": {"success": 27, "total": 27}, "8": {"success": 44, "total": 44}, "10": {"success": 47, "total": 47}, "5": {"success": 224, "total": 224}, "11": {"success": 44, "total": 44}, "7": {"success": 84, "total": 84}, "9": {"success": 83, "total": 83}, "12": {"success": 42, "total": 42}, "16": {"success": 36, "total": 36}, "18": {"success": 31, "total": 31}}, "success_rate": 0.3068}